Metadata-Version: 1.0
Name: gaussian-binomial-dist
Version: 0.1.1
Summary: Gaussian and Binomial distributions
Home-page: UNKNOWN
Author: Bogdan Balcau
Author-email: UNKNOWN
License: UNKNOWN
Platform: UNKNOWN
